[
  {
    "id": "41d8624dbfa9ea28621b36ff325bec37",
    "title": "US civil rights leader Cesar Chavez accused of sexual abuse",
    "description": "The allegations have prompted the cancellations of events and celebrations planned in his honour later this month.",
    "content": "US civil rights leader Cesar Chavez, who was known for advocating for the rights of farm workers, has been accused of sexual abuse.\nDolores Huerta said in the 1960s, Chavez, who co-founded the United Farm Workers union (UFW) with her, once \"manipulat... [2793 chars]",
    "url": "https://www.bbc.co.uk/news/articles/cp8r8rggxmmo",
    "image": "https://ichef.bbci.co.uk/ace/branded_news/1200/cpsprodpb/a8dd/live/c1e897c0-2314-11f1-83bb-2f220ea2da92.jpg",
    "publishedAt": "2026-03-19T00:56:43Z",
    "lang": "en",
    "source": {
      "id": "da05009467a13bbcc84557ea09d86db3",
      "name": "BBC",
      "url": "https://www.bbc.co.uk"
    }
  },
  {
    "id": "6b53fbdacd992d8ae64712a373d5d6b9",
    "title": "Ryan Gosling on blending humour and sci-fi in new film Project Hail Mary",
    "description": "The Canadian actor stars as a science teacher turned astronaut in sci-fi film Project Hail Mary.",
    "content": "Humour and science fiction may not seem obvious bedfellows but a history of cinema will tell you different. Think Spaceballs, Mars Attacks! and Everything Everwhere All At Once to name but a few. And now Ryan Gosling is hopping on board.\nThe 45-year-... [3143 chars]",
    "url": "https://www.bbc.co.uk/news/articles/cm2xrxp3kz0o",
    "image": "https://ichef.bbci.co.uk/ace/branded_news/1200/cpsprodpb/3ad0/live/b38b6670-21e9-11f1-a42b-a3f1101f2a6d.jpg",
    "publishedAt": "2026-03-19T00:53:59Z",
    "lang": "en",
    "source": {
      "id": "da05009467a13bbcc84557ea09d86db3",
      "name": "BBC",
      "url": "https://www.bbc.co.uk"
    }
  },
  {
    "id": "5e583d73b0aac5a387093d99a235a94b",
    "title": "US aircraft carrier to sail for Crete for repairs after fire on board",
    "description": "The USS Gerald R Ford has played a significant role in US operations during the war with Iran.",
    "content": "The US Navy's most advanced aircraft carrier, the USS Gerald R Ford, is preparing to leave the Red Sea for repairs in Crete after a fire on board injured sailors and caused significant damage, US officials have said.\nIt will travel to a US Navy base ... [1748 chars]",
    "url": "https://www.bbc.co.uk/news/articles/c0rjr28nxrwo",
    "image": "https://ichef.bbci.co.uk/ace/branded_news/1200/cpsprodpb/cff3/live/a2371e90-2316-11f1-83bb-2f220ea2da92.jpg",
    "publishedAt": "2026-03-19T00:44:57Z",
    "lang": "en",
    "source": {
      "id": "da05009467a13bbcc84557ea09d86db3",
      "name": "BBC",
      "url": "https://www.bbc.co.uk"
    }
  },
  {
    "id": "0b1ddf043b7d24777051b057a7f9c562",
    "title": "Impact of Iran war expected to bring hold in interest rates",
    "description": "Before the conflict began, analysts had expected a cut in the Bank rate at this meeting.",
    "content": "Economic impacts of the war in Iran are expected to lead the Bank of England to hold interest rates later.\nBefore the conflict began, analysts had predicted a cut in the Bank rate at this meeting, but upheaval in the markets and a higher oil price ha... [2397 chars]",
    "url": "https://www.bbc.co.uk/news/articles/c8d5dee3ep8o",
    "image": "https://ichef.bbci.co.uk/ace/branded_news/1200/cpsprodpb/bbfd/live/920acb20-22b2-11f1-8a6e-abb477324122.jpg",
    "publishedAt": "2026-03-19T00:10:32Z",
    "lang": "en",
    "source": {
      "id": "da05009467a13bbcc84557ea09d86db3",
      "name": "BBC",
      "url": "https://www.bbc.co.uk"
    }
  },
  {
    "id": "da6a93b6cf287d8205062af3621e9449",
    "title": "UK sets targets to boost steel making and cut imports",
    "description": "Up to half of steel used in Britain should be made there, the government says, as it announces its steel strategy.",
    "content": "The government has set a target for the UK make half of the steel it uses and has announced higher taxes on buying steel from overseas.\nImported steel quotas will be lowered and anything brought in above that level will be subject to a new 50% tariff... [3471 chars]",
    "url": "https://www.bbc.co.uk/news/articles/c98q8q4zl8qo",
    "image": "https://ichef.bbci.co.uk/ace/branded_news/1200/cpsprodpb/2f5e/live/6ed1a370-2304-11f1-b297-95b0a0a8331e.jpg",
    "publishedAt": "2026-03-19T00:04:46Z",
    "lang": "en",
    "source": {
      "id": "da05009467a13bbcc84557ea09d86db3",
      "name": "BBC",
      "url": "https://www.bbc.co.uk"
    }
  }
]