[
  {
    "id": "b03b24cb8c02a7885307cd3afdfa4121",
    "title": "Why Croatia's capital wants to hold the best Christmas market",
    "description": "The festive events help to put cities on the map and attract millions of tourists.",
    "content": "Christmas markets are not just tradition across Europe, they are big businesses that give cities a huge economic boost every December. For Zagreb, the capital of Croatia, it is an effective way of attracting tourists outside of the country's main sum... [6216 chars]",
    "url": "https://www.bbc.co.uk/news/articles/c8dy5m56477o",
    "image": "https://ichef.bbci.co.uk/ace/branded_news/1200/cpsprodpb/a02c/live/65887bf0-d9ca-11f0-b67b-690eb873de1b.jpg",
    "publishedAt": "2025-12-22T01:05:38Z",
    "lang": "en",
    "source": {
      "id": "da05009467a13bbcc84557ea09d86db3",
      "name": "BBC",
      "url": "https://www.bbc.co.uk"
    }
  },
  {
    "id": "dfaaaa2860715bde00e6960c3046a7da",
    "title": "University threatened with legal action after protest at event",
    "description": "Prof Alice Sullivan says her talk at the University of Bristol became like a \"zombie apocalypse\" during the protest.",
    "content": "A leading academic, who led a recent government review into sex and gender data collection has threatened legal action against the University of Bristol, claiming it failed to protect her freedom of speech.\nProf Alice Sullivan has also written to the... [5370 chars]",
    "url": "https://www.bbc.co.uk/news/articles/cwyx3y84ln9o",
    "image": "https://ichef.bbci.co.uk/ace/branded_news/1200/cpsprodpb/fed2/live/b8a103a0-dc5b-11f0-93b7-f51fc4e09435.jpg",
    "publishedAt": "2025-12-22T00:08:08Z",
    "lang": "en",
    "source": {
      "id": "da05009467a13bbcc84557ea09d86db3",
      "name": "BBC",
      "url": "https://www.bbc.co.uk"
    }
  },
  {
    "id": "8ba998e1173b10e2c497dd2cd91a07d9",
    "title": "Why our railways often seem to be in such chaos over Christmas",
    "description": "Parts of Britain\u2019s rail network will close for engineering work over the festive period - but is that the right time to do it?",
    "content": "At a rail yard near Milton Keynes, a group of men in orange outfits are making final checks on huge slabs of railway track, preparing them so that they are ready to be installed over Christmas and New Year.\nAt a time when many commuters stop work to ... [8284 chars]",
    "url": "https://www.bbc.co.uk/news/articles/czdg795m5epo",
    "image": "https://ichef.bbci.co.uk/ace/branded_news/1200/cpsprodpb/ff22/live/8a4ad250-dc02-11f0-aae2-2191c0e48a3b.jpg",
    "publishedAt": "2025-12-22T00:03:12Z",
    "lang": "en",
    "source": {
      "id": "da05009467a13bbcc84557ea09d86db3",
      "name": "BBC",
      "url": "https://www.bbc.co.uk"
    }
  },
  {
    "id": "19a19711f64277c63fbbfb28c9c86821",
    "title": "Stranger Things, Amandaland and Strictly Come Dancing",
    "description": "Stranger Things, Two Doors Down and The Celebrity Apprentice are among this year's highlights.",
    "content": "Bake Off, Strictly or Amandaland? The TV highlights over Christmas\n11 hours ago\nSteven McIntoshEntertainment reporter\nWith Mariah Carey fully defrosted and mince pies disappearing at an alarming rate, families everywhere are poring over surely the mo... [7031 chars]",
    "url": "https://www.bbc.com/news/articles/c17xerjryz0o",
    "image": "https://ichef.bbci.co.uk/news/1024/branded_news/be30/live/bd1a2f10-df21-11f0-aae2-2191c0e48a3b.jpg",
    "publishedAt": "2025-12-22T00:03:05Z",
    "lang": "en",
    "source": {
      "id": "f331a5ed3965fb59761dfcecfc7e7a34",
      "name": "BBC",
      "url": "https://www.bbc.com"
    }
  },
  {
    "id": "8e35fb2cca993c54a10c67e45f0c1085",
    "title": "Strictly Come Dancing",
    "description": "Stranger Things, Two Doors Down and The Celebrity Apprentice are among this year's highlights.",
    "content": "With Mariah Carey fully defrosted and mince pies disappearing at an alarming rate, families everywhere are poring over surely the most important item in any household - the Christmas TV listings guide.\nWe won't sugarcoat things - this year's offering... [2841 chars]",
    "url": "https://www.bbc.co.uk/news/articles/c17xerjryz0o",
    "image": "https://ichef.bbci.co.uk/ace/branded_news/1200/cpsprodpb/56e6/live/6812bb30-d9c8-11f0-b67b-690eb873de1b.jpg",
    "publishedAt": "2025-12-22T00:03:05Z",
    "lang": "en",
    "source": {
      "id": "da05009467a13bbcc84557ea09d86db3",
      "name": "BBC",
      "url": "https://www.bbc.co.uk"
    }
  }
]